qwen_vl_utils/__init__.py
qwen_vl_utils/vision_process.py
qwen_vl_utils-0.0.13.dist-info/METADATA
qwen_vl_utils-0.0.13.dist-info/WHEEL
qwen_vl_utils-0.0.13.dist-info/RECORD
