Metadata-Version: 2.4
Name: qwen-vl-utils
Version: 0.0.13
Summary: Qwen Vision Language Model Utils - PyTorch
Project-URL: Homepage, https://github.com/QwenLM/Qwen2-VL/tree/main/qwen-vl-utils
Project-URL: Repository, https://github.com/QwenLM/Qwen2-VL.git
Project-URL: Issues, https://github.com/QwenLM/Qwen2-VL/issues
Author-email: Qwen Team <chenkeqin.ckq@alibaba-inc.com>
License: Apache-2.0
Keywords: large language model,pytorch,qwen-vl,vision language model
Classifier: Development Status :: 4 - Beta
Classifier: License :: OSI Approved :: Apache Software License
Classifier: Programming Language :: Python :: 3
Classifier: Topic :: Scientific/Engineering :: Artificial Intelligence
Requires-Python: >=3.8
Requires-Dist: av
Requires-Dist: packaging
Requires-Dist: pillow
Requires-Dist: requests
Provides-Extra: decord
Requires-Dist: decord; extra == 'decord'
